utilz/__init__.py
utilz/_utils.py
utilz/boilerplate.py
utilz/data.py
utilz/decorators.py
utilz/dev/data.py
utilz/dftools.py
utilz/dfverbs/__init__.py
utilz/dfverbs/plot.py
utilz/dfverbs/stats.py
utilz/dfverbs/verbs.py
utilz/genz.py
utilz/io.py
utilz/maps.py
utilz/ops.py
utilz/pipes.py
utilz/plot.py
utilz/shorts.py
utilz/stats.py
utilz/tests/conftest.py
utilz/tests/mtcars.csv
utilz/tests/test_boilerplate.py
utilz/tests/test_data.py
utilz/tests/test_decorators.py
utilz/tests/test_dftools.py
utilz/tests/test_dfverbs.py
utilz/tests/test_genz.py
utilz/tests/test_io.py
utilz/tests/test_ops.py
utilz/tests/test_plot.py
utilz/tests/test_shorts.py
py_utilz-0.4.1.dist-info/LICENSE
py_utilz-0.4.1.dist-info/METADATA
py_utilz-0.4.1.dist-info/WHEEL
py_utilz-0.4.1.dist-info/RECORD
