Metadata-Version: 2.1
Name: py-utilz
Version: 0.4.1
Summary: Faster, easier, more robust python data analysis
License: MIT
Author: ejolly
Author-email: eshin.jolly@gmail.com
Requires-Python: >=3.8,<4.0
Classifier: License :: OSI Approved :: MIT License
Classifier: Programming Language :: Python :: 3
Classifier: Programming Language :: Python :: 3.8
Classifier: Programming Language :: Python :: 3.9
Classifier: Programming Language :: Python :: 3.10
Classifier: Programming Language :: Python :: 3.11
Requires-Dist: joblib (>=1.1.0,<2.0.0)
Requires-Dist: matplotlib (>=3.1.0,<4.0.0)
Requires-Dist: numpy (>=1.16,<2.0)
Requires-Dist: pandas (>=1.2.0,<2.0.0)
Requires-Dist: seaborn (>=0.12.0)
Requires-Dist: toolz (>=0.12.0,<0.13.0)
Requires-Dist: tqdm (>=4.64.1,<5.0.0)
